{
  "persons": [
		{
      "name": "Arto Hellas",
      "number": "045-406-1756",
      "id": 1
    },
		{
      "name": "Ada Lovelace",
      "number": "397-447-3235",
      "id": 2
    },
		{
      "name": "Dan Abramov",
      "number": "142-435-2345",
      "id": 3
    },
		{
      "name": "Mary Poppendieck",
      "number": "394-263-3122",
      "id": 4
    },
    {
      "name": "alexander",
      "number": "349-256-6422",
      "id": 5
    },
    {
      "name": "susan",
      "number": "779-299-6423",
      "id": 6
    }
	]
}
